etelemetry/__init__.py
etelemetry/_version.py
etelemetry/client.py
etelemetry/config/__init__.py
etelemetry/tests/__init__.py
etelemetry/tests/test_client.py
etelemetry-0.2.1.dist-info/LICENSE
etelemetry-0.2.1.dist-info/METADATA
etelemetry-0.2.1.dist-info/WHEEL
etelemetry-0.2.1.dist-info/top_level.txt
etelemetry-0.2.1.dist-info/RECORD
