Metadata-Version: 2.1
Name: etelemetry
Version: 0.2.1
Summary: Etelemetry python client API
Home-page: https://github.com/sensein/etelemetry-client
Author: Senseable Intelligence Group
Maintainer: Mathias Goncalves
Maintainer-email: mathiasg@mit.edu
License: Apache License, 2.0
Platform: UNKNOWN
Classifier: Development Status :: 3 - Alpha
Classifier: Intended Audience :: Science/Research
Classifier: License :: OSI Approved :: Apache Software License
Classifier: Programming Language :: Python :: 3.5
Classifier: Programming Language :: Python :: 3.6
Classifier: Programming Language :: Python :: 3.7
Provides: etelemetry
Requires-Python: >= 3.5
Provides-Extra: all
Provides-Extra: test
Provides-Extra: tests
